azure/mgmt/managednetworkfabric/__init__.py
azure/mgmt/managednetworkfabric/_configuration.py
azure/mgmt/managednetworkfabric/_managed_network_fabric_mgmt_client.py
azure/mgmt/managednetworkfabric/_patch.py
azure/mgmt/managednetworkfabric/_serialization.py
azure/mgmt/managednetworkfabric/_vendor.py
azure/mgmt/managednetworkfabric/_version.py
azure/mgmt/managednetworkfabric/py.typed
azure/mgmt/managednetworkfabric/aio/__init__.py
azure/mgmt/managednetworkfabric/aio/_configuration.py
azure/mgmt/managednetworkfabric/aio/_managed_network_fabric_mgmt_client.py
azure/mgmt/managednetworkfabric/aio/_patch.py
azure/mgmt/managednetworkfabric/aio/operations/__init__.py
azure/mgmt/managednetworkfabric/aio/operations/_access_control_lists_operations.py
azure/mgmt/managednetworkfabric/aio/operations/_external_networks_operations.py
azure/mgmt/managednetworkfabric/aio/operations/_internal_networks_operations.py
azure/mgmt/managednetworkfabric/aio/operations/_internet_gateway_rules_operations.py
azure/mgmt/managednetworkfabric/aio/operations/_internet_gateways_operations.py
azure/mgmt/managednetworkfabric/aio/operations/_ip_communities_operations.py
azure/mgmt/managednetworkfabric/aio/operations/_ip_extended_communities_operations.py
azure/mgmt/managednetworkfabric/aio/operations/_ip_prefixes_operations.py
azure/mgmt/managednetworkfabric/aio/operations/_l2_isolation_domains_operations.py
azure/mgmt/managednetworkfabric/aio/operations/_l3_isolation_domains_operations.py
azure/mgmt/managednetworkfabric/aio/operations/_neighbor_groups_operations.py
azure/mgmt/managednetworkfabric/aio/operations/_network_device_skus_operations.py
azure/mgmt/managednetworkfabric/aio/operations/_network_devices_operations.py
azure/mgmt/managednetworkfabric/aio/operations/_network_fabric_controllers_operations.py
azure/mgmt/managednetworkfabric/aio/operations/_network_fabric_skus_operations.py
azure/mgmt/managednetworkfabric/aio/operations/_network_fabrics_operations.py
azure_mgmt_managednetworkfabric-1.0.0.dist-info/LICENSE
azure_mgmt_managednetworkfabric-1.0.0.dist-info/METADATA
azure_mgmt_managednetworkfabric-1.0.0.dist-info/WHEEL
azure_mgmt_managednetworkfabric-1.0.0.dist-info/top_level.txt
azure_mgmt_managednetworkfabric-1.0.0.dist-info/RECORD
